README.md
setup.cfg
setup.py
src/guess_the_movie/__init__.py
src/guess_the_movie/controller.py
src/guess_the_movie/main.py
src/guess_the_movie/model.py
src/guess_the_movie/utils.py
src/guess_the_movie.egg-info/PKG-INFO
src/guess_the_movie.egg-info/SOURCES.txt
src/guess_the_movie.egg-info/dependency_links.txt
src/guess_the_movie.egg-info/entry_points.txt
src/guess_the_movie.egg-info/requires.txt
src/guess_the_movie.egg-info/top_level.txt
src/guess_the_movie/data/movies.json
src/guess_the_movie/data/records.json
src/guess_the_movie/view/__init__.py
src/guess_the_movie/view/elements.py
src/guess_the_movie/view/windows.py
src/guess_the_movie/view/uis/__init__.py
src/guess_the_movie/view/uis/difficult_menu.py
src/guess_the_movie/view/uis/game.py
src/guess_the_movie/view/uis/game_over_menu.py
src/guess_the_movie/view/uis/main_menu.py
src/guess_the_movie/view/uis/pause_menu.py
src/guess_the_movie/view/uis/records.py