Metadata-Version: 1.0
Name: guess-the-movie
Version: 0.9
Summary: Game guess the movie by screenshot
Home-page: https://github.com/moevm/gui-1h2018-34
Author: Alexey
Author-email: bagar0x60@gmail.com
License: MIT
Platform: UNKNOWN
